fusion_util/__init__.py
fusion_util/_version.py
fusion_util/cert.py
fusion_util/defer.py
fusion_util/enums.py
fusion_util/errors.py
fusion_util/tap.py
fusion_util/test/__init__.py
fusion_util/test/test_cert.py
fusion_util/test/test_defer.py
fusion_util/test/test_enums.py
fusion_util/test/test_tap.py
fusion_util-1.3.0.dist-info/DESCRIPTION.rst
fusion_util-1.3.0.dist-info/METADATA
fusion_util-1.3.0.dist-info/RECORD
fusion_util-1.3.0.dist-info/WHEEL
fusion_util-1.3.0.dist-info/metadata.json
fusion_util-1.3.0.dist-info/top_level.txt
