Metadata-Version: 2.0
Name: fusion-util
Version: 1.3.0
Summary: Utility package for Fusion
Home-page: https://github.com/fusionapp/fusion-util
Author: UNKNOWN
Author-email: UNKNOWN
License: MIT
Platform: UNKNOWN
Requires-Dist: Twisted[tls] (>=15.0.0)
Requires-Dist: incremental
Requires-Dist: testtools (>=2.1.0)
